.env
Error_Dialog.py
Error_Dialog.ui
MANIFEST
README
Source_Viewer_Dialog.ui
ez_setup.py
known_bugs.txt
listnerlist.lsnr
path_creator
pathlist.path
setup.py
setup_distutils.py
speakerlist.spkr
test.env
test.ses
pathcreator/Audio_Form.ui
pathcreator/Audio_Form_Ui.py
pathcreator/Environment_Form.ui
pathcreator/Environment_Form_Ui.py
pathcreator/Marker_Dialog.ui
pathcreator/Marker_Dialog_Ui.py
pathcreator/Path_Creator.ui
pathcreator/Path_Creator_Ui.py
pathcreator/Path_Point_Dialog.ui
pathcreator/Path_Point_Dialog_Ui.py
pathcreator/Point_Dialog.ui
pathcreator/Point_Dialog_Ui.py
pathcreator/__init__.py
pathcreator/audio_dock.py
pathcreator/audio_dock_test.py
pathcreator/environment_dock_widget.py
pathcreator/environment_dock_widget_test.py
pathcreator/gl_widget.py
pathcreator/marker_dialog.py
pathcreator/marker_dialog_test.py
pathcreator/path_point_dialog.py
pathcreator/path_point_manager.py
pathcreator/pathcreator.py
pathcreator/point3d.py
pathcreator/point_dialog.py
pathcreator/point_dialog_test.py
pathcreator.egg-info/PKG-INFO
pathcreator.egg-info/SOURCES.txt
pathcreator.egg-info/dependency_links.txt
pathcreator.egg-info/requires.txt
pathcreator.egg-info/top_level.txt