Metadata-Version: 1.0
Name: pathcreator
Version: 0.1.12
Summary: Tool to create 3d sound rendering path given a listener, speakers, audio path and audio track.
Home-page: http://vis.uky.edu/
Author: Charles Maynard, Vis Center
Author-email: cmaynard+path_creator@gmail.com
License: UNKNOWN
Platform: UNKNOWN
